mlrose_ky/__init__.py
mlrose_ky/algorithms/__init__.py
mlrose_ky/algorithms/ga.py
mlrose_ky/algorithms/gd.py
mlrose_ky/algorithms/hc.py
mlrose_ky/algorithms/mimic.py
mlrose_ky/algorithms/rhc.py
mlrose_ky/algorithms/sa.py
mlrose_ky/algorithms/crossovers/__init__.py
mlrose_ky/algorithms/crossovers/_crossover_base.py
mlrose_ky/algorithms/crossovers/one_point_crossover.py
mlrose_ky/algorithms/crossovers/tsp_crossover.py
mlrose_ky/algorithms/crossovers/uniform_crossover.py
mlrose_ky/algorithms/decay/__init__.py
mlrose_ky/algorithms/decay/arith_decay.py
mlrose_ky/algorithms/decay/custom_schedule.py
mlrose_ky/algorithms/decay/exp_decay.py
mlrose_ky/algorithms/decay/geom_decay.py
mlrose_ky/algorithms/mutators/__init__.py
mlrose_ky/algorithms/mutators/_mutator_base.py
mlrose_ky/algorithms/mutators/change_one_mutator.py
mlrose_ky/algorithms/mutators/discrete_mutator.py
mlrose_ky/algorithms/mutators/shift_one_mutator.py
mlrose_ky/algorithms/mutators/swap_mutator.py
mlrose_ky/decorators/__init__.py
mlrose_ky/decorators/short_name_decorator.py
mlrose_ky/fitness/__init__.py
mlrose_ky/fitness/_discrete_peaks_base.py
mlrose_ky/fitness/continuous_peaks.py
mlrose_ky/fitness/custom_fitness.py
mlrose_ky/fitness/flip_flop.py
mlrose_ky/fitness/four_peaks.py
mlrose_ky/fitness/knapsack.py
mlrose_ky/fitness/max_k_color.py
mlrose_ky/fitness/one_max.py
mlrose_ky/fitness/queens.py
mlrose_ky/fitness/six_peaks.py
mlrose_ky/fitness/travelling_sales.py
mlrose_ky/generators/__init__.py
mlrose_ky/generators/continuous_peaks_generator.py
mlrose_ky/generators/flip_flop_generator.py
mlrose_ky/generators/four_peaks_generator.py
mlrose_ky/generators/knapsack_generator.py
mlrose_ky/generators/max_k_color_generator.py
mlrose_ky/generators/one_max_generator.py
mlrose_ky/generators/queens_generator.py
mlrose_ky/generators/six_peaks_generator.py
mlrose_ky/generators/tsp_generator.py
mlrose_ky/gridsearch/__init__.py
mlrose_ky/gridsearch/grid_search_mixin.py
mlrose_ky/neural/__init__.py
mlrose_ky-1.1.6.dist-info/LICENSE
mlrose_ky-1.1.6.dist-info/METADATA
mlrose_ky-1.1.6.dist-info/WHEEL
mlrose_ky-1.1.6.dist-info/top_level.txt
mlrose_ky-1.1.6.dist-info/RECORD
