Metadata-Version: 2.1
Name: mlrose-ky
Version: 1.1.6
Summary: MLROSe-ky: Machine Learning, Randomized Optimization and Search
Author-email: Kyle Nakamura <knakamura13dev@gmail.com>
Maintainer-email: Kyle Nakamura <knakamura13dev@gmail.com>
License: BSD-3-Clause
Project-URL: Homepage, https://github.com/knakamura13/mlrose-ky
Project-URL: Issues, https://github.com/knakamura13/mlrose-ky/issues
Project-URL: Documentation, https://nkapila6.github.io/mlrose-ky/
Keywords: machine learning,ML,randomized optimization,search algorithms,neural networks,genetic algorithm,simulated annealing,hill climbing,MIMIC,Python,OMSCS,CS,7641,mlrose-hiive,mlrose-ky
Classifier: Intended Audience :: Education
Classifier: Intended Audience :: Science/Research
Classifier: Natural Language :: English
Classifier: License :: OSI Approved :: BSD License
Classifier: Programming Language :: Python
Classifier: Programming Language :: Python :: 3
Classifier: Topic :: Scientific/Engineering
Classifier: Topic :: Scientific/Engineering :: Artificial Intelligence
Classifier: Topic :: Scientific/Engineering :: Mathematics
Classifier: Topic :: Software Development :: Libraries
Classifier: Topic :: Software Development :: Libraries :: Python Modules
Requires-Python: >=3.10
License-File: LICENSE
Requires-Dist: joblib
Requires-Dist: matplotlib
Requires-Dist: networkx
Requires-Dist: numpy
Requires-Dist: pandas
Requires-Dist: scikit-learn
Requires-Dist: scipy
